.coveragerc
.stestr.conf
AUTHORS
ChangeLog
HACKING.rst
LICENSE
README.rst
manage.py
requirements.txt
setup.cfg
setup.py
start.py
test-requirements.txt
tox.ini
upper-constraints.txt
xerox.xmind
PyXerox.egg-info/PKG-INFO
PyXerox.egg-info/SOURCES.txt
PyXerox.egg-info/dependency_links.txt
PyXerox.egg-info/entry_points.txt
PyXerox.egg-info/not-zip-safe
PyXerox.egg-info/pbr.json
PyXerox.egg-info/requires.txt
PyXerox.egg-info/top_level.txt
config-generator/xerox-policy-generator.conf
config-generator/xerox.conf
etc/xerox.conf.sample
etc/xerox.policy.yaml.sample
xerox/__init__.py
xerox/exception.py
xerox/i18n.py
xerox/notifications.py
xerox/version.py
xerox/api/__init__.py
xerox/api/languages.py
xerox/command/__init__.py
xerox/command/base.py
xerox/command/manage/__init__.py
xerox/command/manage/db_sync.py
xerox/command/manage/db_version.py
xerox/common/__init__.py
xerox/common/authorization.py
xerox/common/context.py
xerox/common/driver_hints.py
xerox/common/json_home.py
xerox/common/manager.py
xerox/common/profiler.py
xerox/common/provider_api.py
xerox/common/utils.py
xerox/common/cache/__init__.py
xerox/common/cache/_context_cache.py
xerox/common/cache/core.py
xerox/common/policies/__init__.py
xerox/common/policies/base.py
xerox/common/policies/language.py
xerox/common/rbac_enforcer/__init__.py
xerox/common/rbac_enforcer/enforcer.py
xerox/common/rbac_enforcer/policy.py
xerox/common/sql/__init__.py
xerox/common/sql/core.py
xerox/common/sql/upgrades.py
xerox/common/sql/contract_repo/README
xerox/common/sql/contract_repo/__init__.py
xerox/common/sql/contract_repo/manage.py
xerox/common/sql/contract_repo/migrate.cfg
xerox/common/sql/contract_repo/versions/001_placeholder.py
xerox/common/sql/contract_repo/versions/002_placeholder.py
xerox/common/sql/contract_repo/versions/003_placeholder.py
xerox/common/sql/contract_repo/versions/004_placeholder.py
xerox/common/sql/contract_repo/versions/005_placeholder.py
xerox/common/sql/contract_repo/versions/006_placeholder.py
xerox/common/sql/contract_repo/versions/007_placeholder.py
xerox/common/sql/contract_repo/versions/008_placeholder.py
xerox/common/sql/contract_repo/versions/009_placeholder.py
xerox/common/sql/contract_repo/versions/010_placeholder.py
