Metadata-Version: 2.1
Name: PyXerox
Version: 0.0.1.dev2
Summary: OpenStack Xerox
Home-page: http://www.slicloud.com:38876/muxin/xerox
Author: imuxin
Author-email: chengqinglin@icloud.com
License: UNKNOWN
Platform: UNKNOWN
Classifier: Environment :: OpenStack
Classifier: Intended Audience :: Information Technology
Classifier: Intended Audience :: System Administrators
Classifier: License :: OSI Approved :: MIT License
Classifier: Operating System :: POSIX :: Linux
Classifier: Programming Language :: Python
Classifier: Programming Language :: Python :: 2
Classifier: Programming Language :: Python :: 2.7
Classifier: Programming Language :: Python :: 3
Classifier: Programming Language :: Python :: 3.6
Classifier: Programming Language :: Python :: 3.7
Provides-Extra: test
Provides-Extra: bandit
Provides-Extra: mongodb
Provides-Extra: memcache
